SOP_GEN/GEN_SOP.py
SOP_GEN/__init__.py
DansonGo_5-0.0.21.dist-info/METADATA
DansonGo_5-0.0.21.dist-info/WHEEL
DansonGo_5-0.0.21.dist-info/top_level.txt
DansonGo_5-0.0.21.dist-info/RECORD
