Metadata-Version: 2.1
Name: DansonGo-5
Version: 0.0.21
Summary: A simple module for generating a bunch of SOPs for different schools.
Home-page: https://github.com/gen-li/SOP_GEN
Author: Gen Li
Author-email: gen.li@yale.edu
License: UNKNOWN
Platform: UNKNOWN
Classifier: Programming Language :: Python :: 3
Classifier: License :: OSI Approved :: MIT License
Classifier: Operating System :: OS Independent
Requires-Python: >=3.6
